yrb/__init__.py
yrb/adapter/__init__.py
yrb/adapter/conda_adapter.py
yrb/adapter/pdm_adapter.py
yrb/adapter/pip_adapter.py
yrb/adapter/poetry_adapter.py
yrb/adapter/uv_adapter.py
yrb/cli/__init__.py
yrb/cli/cli.py
yrb/cli/exception_handler.py
yrb/core/__init__.py
yrb/core/cache_manager.py
yrb/core/config_manager.py
yrb/core/mirror_pool.py
yrb/core/resume_download.py
yrb/core/speed_test.py
yrb-1.4.0.dist-info/licenses/LICENSE
yrb-1.4.0.dist-info/METADATA
yrb-1.4.0.dist-info/WHEEL
yrb-1.4.0.dist-info/entry_points.txt
yrb-1.4.0.dist-info/top_level.txt
yrb-1.4.0.dist-info/RECORD
