Metadata-Version: 2.4
Name: yrb
Version: 1.4.0
Summary: Python第三方库国内下载加速工具
Author-email: "杨如斌 (Rubin Yang)" <2037578680@qq.com>
License: MIT
Project-URL: Homepage, https://github.com/hello-ang/yrb
Project-URL: Source, https://github.com/hello-ang/yrb
Project-URL: Issues, https://github.com/hello-ang/yrb/issues
Requires-Python: >=3.8
License-File: LICENSE
Requires-Dist: requests>=2.32.4
Requires-Dist: click>=8.0.0
Requires-Dist: platformdirs>=3.0.0
Dynamic: license-file
